{
  "id": "sunert.app.sub", 
  "author": "@Sunert", 
  "icon": "https://avatars2.githubusercontent.com/u/47924389?s=460&u=5152f048a9e8aaa45102763a578172407c40fcc8&v=4", 
  "name": "Sunert 签到应用订阅", 
  "repo": "https://github.com/Sunert/Script/tree/master", 
  "apps": [
    {
      "author": "@sunert", 
      "descs_html": [
        "<h4 align=\"center\">获取Cookie以及脚本配置请查看<a href=\"https://github.com/Sunert/Script/raw/master/TaskConf/sina/readme.md\">配置说明</a></h4>", 
        "<br />", 
        "<p>其中<font color='#FF0000',font-weight: bold>wb_nick</font>为账号昵称，无需另外获取，脚本运行可自动生成，wb_cookie为任务红包余额，获取后方可显示，可选，sy_token_wb为微博签到token，必选</p>"
      ], 
      "keys": [
        "sy_token_wb", 
        "wb_cookie", 
        "wb_nick"
      ], 
      "repo": "https://github.com/Sunert/Script/blob/master/Task/weibo.js", 
      "id": "weibo", 
      "script": "https://raw.githubusercontent.com/Sunert/Script/master/Task/weibo.js", 
      "name": "新浪微博", 
      "icons": [
        "https://cdn.jsdelivr.net/gh/Orz-3/mini@master/Alpha/weibo.png", 
        "https://cdn.jsdelivr.net/gh/Orz-3/mini@master/Color/weibo.png"
      ]
    }, 
    {
      "id": "blackmatrix7.smzdm",
      "name": "什么值得买",
      "keys": ["smzdm_cookie", "smzdm_session"],
      "author": "@blackmatrix7",
      "repo": "https://github.com/blackmatrix7/ios_rule_script/tree/master/script/smzdm",
      "icons": ["https://raw.githubusercontent.com/Orz-3/mini/master/Alpha/smzdm.png", "https://raw.githubusercontent.com/Orz-3/mini/master/Color/smzdm.png"],
      "scripts": [
        {
          "name": "每日自动任务",
          "script": "https://raw.githubusercontent.com/blackmatrix7/ios_rule_script/master/script/smzdm/smzdm_mission.js"
        },
        {
          "name": "每日自动签到",
          "script": "https://raw.githubusercontent.com/blackmatrix7/ios_rule_script/master/script/smzdm/smzdm_signin.js"
        }
      ]
    },
    {
      "id": "videoqq",
      "name": "腾讯视频",
      "keys": [
        "chavy_cookie_videoqq",
        "chavy_auth_url_videoqq",
        "chavy_auth_header_videoqq",
        "chavy_msign_url_videoqq",
        "chavy_msign_header_videoqq"
      ],
      "author": "@chavyleung",
      "repo": "https://github.com/chavyleung/scripts/tree/master/videoqq",
      "script": "https://raw.githubusercontent.com/chavyleung/scripts/master/videoqq/videoqq.js",
      "icons": [
        "https://raw.githubusercontent.com/Orz-3/mini/master/Alpha/videoqq.png",
        "https://raw.githubusercontent.com/Orz-3/mini/master/Color/videoqq.png"
      ]
    },
    {
      "id": "NeteaseMusic",
      "name": "网易云音乐",
      "keys": ["chavy_cookie_neteasemusic"],
      "settings": [
        { "id": "CFG_neteasemusic_retryCnt", "name": "重试次数", "val": 10, "type": "text", "desc": "一直尝试签到直至出现“重复签到”标识!" },
        {
          "id": "CFG_neteasemusic_retryInterval",
          "name": "重试间隔 (毫秒)",
          "val": 500,
          "type": "text",
          "desc": "每次重试间隔时间 (毫秒)！"
        }
      ],
      "author": "@chavyleung",
      "repo": "https://github.com/chavyleung/scripts/tree/master/neteasemusic",
      "script": "https://raw.githubusercontent.com/chavyleung/scripts/master/neteasemusic/neteasemusic.js",
      "icons": [
        "https://raw.githubusercontent.com/Orz-3/mini/master/Alpha/neteasemusic.png",
        "https://raw.githubusercontent.com/Orz-3/mini/master/Color/neteasemusic.png"
      ]
    },
    {
      "id": "ximalaya",
      "name": "喜马拉雅",
      "keys": ["chavy_cookie_ximalaya"],
      "author": "@chavyleung",
      "repo": "https://github.com/chavyleung/scripts/tree/master/ximalaya",
      "icons": [
        "https://raw.githubusercontent.com/Orz-3/mini/master/Alpha/ximalaya.png",
        "https://raw.githubusercontent.com/Orz-3/mini/master/Color/ximalaya.png"
      ],
      "script": "https://raw.githubusercontent.com/chavyleung/scripts/master/ximalaya/ximalaya.js"
    },
    {
      "id": "chavyleung.bilibili.live",
      "name": "bilibili直播",
      "keys": ["chavy_cookie_bilibili"],
      "author": "@chavyleung",
      "repo": "https://github.com/chavyleung/scripts/blob/master/bilibili/bilibili.js",
      "script": "https://raw.githubusercontent.com/chavyleung/scripts/master/bilibili/bilibili.js",
      "icons": [
        "https://raw.githubusercontent.com/Orz-3/mini/master/Alpha/bilibili.png",
        "https://raw.githubusercontent.com/Orz-3/mini/master/Color/bilibili.png"
      ]
    },
    {
      "id": "V2EX",
      "name": "V2EX",
      "keys": ["chavy_cookie_v2ex"],
      "author": "@chavyleung",
      "repo": "https://github.com/chavyleung/scripts/tree/master/v2ex",
      "script": "https://raw.githubusercontent.com/chavyleung/scripts/master/v2ex/v2ex.js",
      "icons": [
        "https://raw.githubusercontent.com/Orz-3/mini/master/Alpha/v2ex.png",
        "https://raw.githubusercontent.com/Orz-3/mini/master/Color/v2ex.png"
      ]
    }
  ]
}
